{
  "building_address": {
    "address": "1 API House", 
    "city": "Minden", 
    "state": "NE", 
    "zip_code": "68959", 
    "assessment_type": "initial"
  }, 
  "building": {
    "about": {
      "assessment_date": "2014-10-23", 
      "shape": "rectangle", 
      "year_built": 1953, 
      "number_bedrooms": 3, 
      "num_floor_above_grade": 2, 
      "floor_to_ceiling_height": 11, 
      "conditioned_floor_area": 1620, 
      "orientation": "east", 
      "blower_door_test": false, 
      "air_sealing_present": false
    }, 
    "zone": {
      "zone_roof": [
        {
          "roof_name": "roof1", 
          "roof_area": 810, 
          "roof_assembly_code": "rfrb00co", 
          "roof_color": "dark", 
          "roof_type": "vented_attic", 
          "ceiling_assembly_code": "ecwf11", 
          "zone_skylight": {
            "skylight_area": 0
          }
        }
      ], 
      "zone_floor": {
        "foundation_type": "vented_crawl", 
        "foundation_insulation_level": 0, 
        "floor_assembly_code": "efwf15ca"
      }, 
      "wall_construction_same": false, 
      "window_construction_same": false, 
      "zone_wall": [
        {
          "side": "left", 
          "wall_assembly_code": "ewwf00br", 
          "zone_window": {
            "window_area": 45.0, 
            "window_method": "code", 
            "window_code": "dcaa"
          }
        }, 
        {
          "side": "front", 
          "wall_assembly_code": "ewwf00br", 
          "zone_window": {
            "window_area": 108.0, 
            "window_method": "code", 
            "window_code": "dcaa"
          }
        }, 
        {
          "side": "right", 
          "wall_assembly_code": "ewwf00br", 
          "zone_window": {
            "window_area": 60.0, 
            "window_method": "code", 
            "window_code": "dcaw"
          }
        }, 
        {
          "side": "back", 
          "wall_assembly_code": "ewwf00br", 
          "zone_window": {
            "window_area": 135.3333333, 
            "window_method": "code", 
            "window_code": "stnw"
          }
        }
      ]
    }, 
    "systems": {
      "heating": {
        "efficiency_method": "user", 
        "efficiency": 0.92, 
        "fuel_primary": "natural_gas", 
        "type": "central_furnace"
      }, 
      "cooling": {
        "type": "split_dx", 
        "efficiency": 13.0, 
        "efficiency_method": "user"
      }, 
      "hvac_distribution": [
        {
          "name": "duct1", 
          "location": "vented_crawl", 
          "fraction": 50, 
          "insulated": true, 
          "sealed": true
        }, 
        {
          "name": "duct2", 
          "location": "uncond_attic", 
          "fraction": 35, 
          "insulated": true, 
          "sealed": true
        }, 
        {
          "name": "duct3", 
          "location": "cond_space", 
          "fraction": 15, 
          "insulated": false, 
          "sealed": true
        }
      ], 
      "domestic_hot_water": {
        "category": "unit", 
        "type": "storage", 
        "fuel_primary": "electric", 
        "efficiency_method": "user", 
        "energy_factor": 0.8
      }
    }
  }
}